charfreq/__main__.py
charfreq/run.py
charfreq-23.8.2.dist-info/METADATA
charfreq-23.8.2.dist-info/WHEEL
charfreq-23.8.2.dist-info/entry_points.txt
charfreq-23.8.2.dist-info/licenses/LICENSE
charfreq-23.8.2.dist-info/RECORD
