Metadata-Version: 2.1
Name: charfreq
Version: 23.8.2
Summary: Get character frequency inside files
Project-URL: Repository, https://github.com/mark-bromell/charfreq
Project-URL: Bug Tracker, https://github.com/mark-bromell/charfreq/issues
Author: Mark Bromell
License: Copyright (c) 2012-2023 Mark Bromell
License-File: LICENSE
Classifier: License :: OSI Approved :: MIT License
Classifier: Operating System :: OS Independent
Classifier: Programming Language :: Python :: 3
Requires-Python: >=3.8
